main.py
simple_text_replacer-1.0.0.dist-info/licenses/LICENSE.txt
simple_text_replacer-1.0.0.dist-info/METADATA
simple_text_replacer-1.0.0.dist-info/WHEEL
simple_text_replacer-1.0.0.dist-info/entry_points.txt
simple_text_replacer-1.0.0.dist-info/top_level.txt
simple_text_replacer-1.0.0.dist-info/RECORD
