Metadata-Version: 2.4
Name: simple-text-replacer
Version: 1.0.0
Summary: This provides text replacement by YAML or JSON format.
Author-email: masaniki <masaniki.software@gmail.com>
License-Expression: MIT
Project-URL: Repository, https://github.com/masaniki/simple-text-replacer
Project-URL: Documentation, https://github.com/masaniki/simple-text-replacer/blob/master/README.md
Project-URL: Issues, https://github.com/masaniki/simple-text-replacer/issues
Keywords: text,CLI
Classifier: Development Status :: 1 - Planning
Classifier: Environment :: Console
Classifier: Programming Language :: Python :: 3.9
Classifier: Topic :: Text Processing
Classifier: Natural Language :: Japanese
Classifier: Natural Language :: English
Requires-Python: >=3.9
License-File: LICENSE.txt
Requires-Dist: PyYAML
Dynamic: license-file
